CONTRIBUTING.rst
HISTORY.rst
LICENSE
MANIFEST.in
README.rst
setup.cfg
setup.py
docs/Makefile
docs/conf.py
docs/contributing.rst
docs/history.rst
docs/index.rst
docs/installation.rst
docs/make.bat
docs/readme.rst
docs/usage.rst
tests/.test_thrift_json.py.swp
tests/__init__.py
tests/features.thrift
tests/test_thrift_json.py
tests/features/__init__.py
tests/features/constants.py
tests/features/ttypes.py
thrift_json/__init__.py
thrift_json/formatter.py
thrift_json/parser.py
thrift_json.egg-info/PKG-INFO
thrift_json.egg-info/SOURCES.txt
thrift_json.egg-info/dependency_links.txt
thrift_json.egg-info/not-zip-safe
thrift_json.egg-info/requires.txt
thrift_json.egg-info/top_level.txt