Metadata-Version: 1.1
Name: thrift-json
Version: 0.1.0
Summary: converter between thrift and json
Home-page: https://github.com/youngking/thrift_json
Author: Young King
Author-email: yanckin@gmail.com
License: MIT license
Keywords: thrift_json
Platform: UNKNOWN
Classifier: Development Status :: 2 - Pre-Alpha
Classifier: Intended Audience :: Developers
Classifier: License :: OSI Approved :: MIT License
Classifier: Natural Language :: English
Classifier: Programming Language :: Python :: 2
Classifier: Programming Language :: Python :: 2.6
Classifier: Programming Language :: Python :: 2.7
Classifier: Programming Language :: Python :: 3
Classifier: Programming Language :: Python :: 3.3
Classifier: Programming Language :: Python :: 3.4
Classifier: Programming Language :: Python :: 3.5
